sf_tensor/__init__.py
sf_tensor/example.py
sf_tensor-0.0.1.dist-info/METADATA
sf_tensor-0.0.1.dist-info/WHEEL
sf_tensor-0.0.1.dist-info/licenses/LICENSE
sf_tensor-0.0.1.dist-info/RECORD
