Metadata-Version: 2.4
Name: sf-tensor
Version: 0.0.1
Summary: The SF Tensor package
Project-URL: Homepage, https://sf-tensor.com
License: MIT License
License-File: LICENSE
Keywords: example,packaging,tutorial
Classifier: License :: OSI Approved :: MIT License
Classifier: Operating System :: OS Independent
Classifier: Programming Language :: Python :: 3
Requires-Python: >=3.8
